onefuzz/__init__.py
onefuzz/__main__.py
onefuzz/__version__.py
onefuzz/api.py
onefuzz/azcopy.py
onefuzz/azure_identity_credential_adapter.py
onefuzz/backend.py
onefuzz/cli.py
onefuzz/debug.py
onefuzz/opentelemetry_exporter.py
onefuzz/rdp.py
onefuzz/ssh.py
onefuzz/template.py
onefuzz/data/licenses.json
onefuzz/data/privacy.txt
onefuzz/job_templates/__init__.py
onefuzz/job_templates/builder.py
onefuzz/job_templates/cache.py
onefuzz/job_templates/handlers.py
onefuzz/job_templates/job_monitor.py
onefuzz/job_templates/main.py
onefuzz/job_templates/manage.py
onefuzz/status/__init__.py
onefuzz/status/cache.py
onefuzz/status/cmd.py
onefuzz/status/raw.py
onefuzz/status/signalr.py
onefuzz/status/top.py
onefuzz/status/top_view.py
onefuzz/templates/__init__.py
onefuzz/templates/afl.py
onefuzz/templates/libfuzzer.py
onefuzz/templates/ossfuzz.py
onefuzz/templates/radamsa.py
onefuzz/templates/regression.py
tests/__init__.py
tests/test_template_helper.py
onefuzz-9.0.0.dist-info/LICENSE
onefuzz-9.0.0.dist-info/METADATA
onefuzz-9.0.0.dist-info/WHEEL
onefuzz-9.0.0.dist-info/entry_points.txt
onefuzz-9.0.0.dist-info/top_level.txt
onefuzz-9.0.0.dist-info/RECORD
