Metadata-Version: 2.1
Name: onefuzz
Version: 9.0.0
Summary: Onefuzz Client Library for Python
Home-page: https://github.com/microsoft/onefuzz/
Author: Microsoft Corporation
Author-email: fuzzing@microsoft.com
License: MIT
License-File: LICENSE
Requires-Dist: msal ==1.22.0
Requires-Dist: requests >=2.31.0
Requires-Dist: jmespath ~=0.10.0
Requires-Dist: semver ~=2.13.0
Requires-Dist: signalrcore ==0.9.2
Requires-Dist: asciimatics ~=1.13.0
Requires-Dist: pydantic ~=1.8.1
Requires-Dist: memoization ~=0.4.0
Requires-Dist: msrestazure ==0.6.4
Requires-Dist: azure-storage-blob ==12.14.1
Requires-Dist: azure-applicationinsights ==0.1.0
Requires-Dist: tenacity ==8.0.1
Requires-Dist: docstring-parser ==0.8.1
Requires-Dist: azure-identity ==1.14.0
Requires-Dist: azure-cli-core ==2.50.0
Requires-Dist: PyJWT >=2.4.0
Requires-Dist: opentelemetry-api ==1.16.0
Requires-Dist: opentelemetry-sdk ==1.16.0
Requires-Dist: opentelemetry-instrumentation-requests ==0.37b0
Requires-Dist: rsa >=4.7
Requires-Dist: onefuzztypes ==9.0.*
